src/parameters.v
// OPCODES in bits
`define OP_ADD 3'b000
`define OP_SUB 3'b001
`define OP_AND 3'b010
`define OP_OR  3'b011
`define OP_LOAD 3'b100
`define OP_STORE 3'b101
`define OP_JMP 3'b110
`define OP_BEQ 3'b111

`define R0_SELECTOR 3'b000
`define R1_SELECTOR 3'b001
`define R2_SELECTOR 3'b010
`define R3_SELECTOR  3'b011
`define R4_SELECTOR 3'b100
`define R5_SELECTOR 3'b101
`define R6_SELECTOR 3'b110
`define R7_SELECTOR 3'b111

// SC States
`define T0 2'b00
`define T1 2'b01
`define T2 2'b10
`define T3 2'b11

src/alu.v
`include "parameters.v" 

module alu(
 input wire enable,
 input wire clk,
 input wire [2:0] mode,
 input wire [7:0] in_a,
 input wire [7:0] in_b,
 output wire [7:0] out,
 output reg flag_zero,
 output reg flag_carry
);

// alu alu_instance(
//     enable(),
//     clk(),
//     mode(),
//     in_a(),
//     in_b(),
//     out(),
//     flag_zero(),
//     flag_carry()
// );

 reg [7:0] buf_out;

 initial begin
   flag_carry = 0;
   flag_zero = 0;
 end

 always @(posedge clk) begin
   if (enable) begin
     case (mode)
       `OP_ADD: {flag_carry, buf_out} = in_a + in_b;
       `OP_SUB: {flag_carry, buf_out} = in_a - in_b;
       `OP_AND: buf_out = in_a & in_b;
       `OP_OR:  buf_out = in_a | in_b;
       default:  buf_out = 'hxx;
     endcase

     flag_zero = (buf_out == 0) ? 1 : 0;

   end
 end
 assign out = buf_out;

endmodule

test/alu_tb.v
module alu_tb;
    // Inputs
    reg enable;
    reg clk;
    reg [2:0] mode;
    reg [7:0] in_a;
    reg [7:0] in_b;

    // Outputs
    wire [7:0] out;
    wire flag_zero;
    wire flag_carry;

    // Instantiate the ALU (Unit Under Test)
    alu uut (
        .enable(enable),
        .clk(clk),
        .mode(mode),
        .in_a(in_a),
        .in_b(in_b),
        .out(out),
        .flag_zero(flag_zero),
        .flag_carry(flag_carry)
    );

    initial begin
        // Initialize Inputs
        enable = 0;
        clk = 0;
        mode = 0;
        in_a = 0;
        in_b = 0;

        // Generate VCD file
        $dumpfile("alu_tb.vcd");
        $dumpvars(0, alu_tb);

        // Apply test vectors
        #10 enable = 1; mode = `OP_ADD; in_a = 8'h0F; in_b = 8'h01;
        #10 clk = 1; #10 clk = 0;

        #10 enable = 1; mode = `OP_SUB; in_a = 8'h10; in_b = 8'h01;
        #10 clk = 1; #10 clk = 0;

        #10 enable = 1; mode = `OP_AND; in_a = 8'hF0; in_b = 8'h0F;
        #10 clk = 1; #10 clk = 0;

        #10 enable = 1; mode = `OP_OR;  in_a = 8'hF0; in_b = 8'h0F;
        #10 clk = 1; #10 clk = 0;

        // Test for zero flag
        #10 enable = 1; mode = `OP_SUB; in_a = 8'h01; in_b = 8'h01;
        #10 clk = 1; #10 clk = 0;

        // Disable ALU
        #10 enable = 0; mode = `OP_ADD; in_a = 8'hFF; in_b = 8'h01;
        #10 clk = 1; #10 clk = 0;

        // Finish simulation
        #10 $finish;
    end

    always #5 clk = ~clk; // Generate clock signal

endmodule

vcd/alu_tb.vcd
$date
	Sat Jun 15 21:54:15 2024
$end
$version
	Icarus Verilog
$end
$timescale
	1s
$end
$scope module alu_tb $end
$var wire 8 ! out [7:0] $end
$var wire 1 " flag_zero $end
$var wire 1 # flag_carry $end
$var reg 1 $ clk $end
$var reg 1 % enable $end
$var reg 8 & in_a [7:0] $end
$var reg 8 ' in_b [7:0] $end
$var reg 3 ( mode [2:0] $end
$scope module uut $end
$var wire 1 $ clk $end
$var wire 1 % enable $end
$var wire 8 ) in_a [7:0] $end
$var wire 8 * in_b [7:0] $end
$var wire 3 + mode [2:0] $end
$var wire 8 , out [7:0] $end
$var reg 8 - buf_out [7:0] $end
$var reg 1 # flag_carry $end
$var reg 1 " flag_zero $end
$upscope $end
$upscope $end
$enddefinitions $end
$comment Show the parameter values. $end
$dumpall
$end
#0
$dumpvars
bx -
bx ,
b0 +
b0 *
b0 )
b0 (
b0 '
b0 &
0%
0$
0#
0"
bx !
$end
#5
1$
#10
0$
b1 '
b1 *
b1111 &
b1111 )
1%
#15
b10000 !
b10000 ,
b10000 -
1$
#20
0$
#25
1$
#30
1$
#35
0$
#40
b1111 !
b1111 ,
b1111 -
1$
b10000 &
b10000 )
b1 (
b1 +
#45
0$
#50
0$
#55
1$
#60
1$
#65
0$
#70
1"
b0 !
b0 ,
b0 -
1$
b1111 '
b1111 *
b11110000 &
b11110000 )
b10 (
b10 +
#75
0$
#80
0$
#85
1$
#90
1$
#95
0$
#100
0"
b11111111 !
b11111111 ,
b11111111 -
1$
b11 (
b11 +
#105
0$
#110
0$
#115
1$
#120
1$
#125
0$
#130
1"
b0 !
b0 ,
b0 -
1$
b1 '
b1 *
b1 &
b1 )
b1 (
b1 +
#135
0$
#140
0$
#145
1$
#150
1$
#155
0$
#160
1$
b11111111 &
b11111111 )
b0 (
b0 +
0%
