src/memory.v
module memory (
    input wire clk,
    input wire mem_write,
    input wire [7:0] address,
    input wire [7:0] input_data,
    output reg [7:0] output_data
);

    reg [7:0] mem [0:255]; // 256 bytes of memory

    always @(posedge clk) begin
        if (mem_write) begin
            mem[address] <= input_data;
        end
        
        output_data = mem[address]; // Continuous assignment for read operation
    end

endmodule

test/memory_tb.v
`timescale 1ns / 1ps

module memory_tb;

    // Parameters
    parameter CLK_PERIOD = 10; // Clock period in time units

    // Signals
    reg clk;
    reg mem_write;
    reg [7:0] address;
    reg [7:0] input_data;
    wire [7:0] output_data;

    // Instantiate memory module
    memory dut (
        .clk(clk),
        .mem_write(mem_write),
        .address(address),
        .input_data(input_data),
        .output_data(output_data)
    );

    // Stimulus
    initial begin
        clk = 0;
        $dumpfile("memory_tb.vcd");
        $dumpvars(0, memory_tb);

        // Write operations
        mem_write = 1;
        address = 8'h00;
        input_data = 8'hAA;
        #20;
        
        mem_write = 1;
        address = 8'hFF;
        input_data = 8'h55;
        #20;
        
        mem_write = 1;
        address = 8'h0A;
        input_data = 8'hF0;
        #20;
        
        mem_write = 0;

        // Read operations
        mem_write = 0;
        address = 8'h00;
        #20;
        
        mem_write = 0;
        address = 8'hFF;
        #20;
        
        mem_write = 0;
        address = 8'h0A;
        #20;

        // Further tests can be added here

        // End simulation
        #100;
        $finish;
    end

    always #5 clk = ~clk;

endmodule

vcd/memory_tb.vcd
$date
	Sun Jun 16 23:44:35 2024
$end
$version
	Icarus Verilog
$end
$timescale
	1ps
$end
$scope module memory_tb $end
$var wire 8 ! output_data [7:0] $end
$var parameter 32 " CLK_PERIOD $end
$var reg 8 # address [7:0] $end
$var reg 1 $ clk $end
$var reg 8 % input_data [7:0] $end
$var reg 1 & mem_write $end
$scope module dut $end
$var wire 8 ' address [7:0] $end
$var wire 1 $ clk $end
$var wire 8 ( input_data [7:0] $end
$var wire 1 & mem_write $end
$var reg 8 ) output_data [7:0] $end
$upscope $end
$upscope $end
$enddefinitions $end
$comment Show the parameter values. $end
$dumpall
b1010 "
$end
#0
$dumpvars
bx )
b10101010 (
b0 '
1&
b10101010 %
0$
b0 #
bx !
$end
#5000
1$
#10000
0$
#15000
b10101010 !
b10101010 )
1$
#20000
0$
b1010101 %
b1010101 (
b11111111 #
b11111111 '
#25000
bx !
bx )
1$
#30000
0$
#35000
b1010101 !
b1010101 )
1$
#40000
0$
b11110000 %
b11110000 (
b1010 #
b1010 '
#45000
bx !
bx )
1$
#50000
0$
#55000
b11110000 !
b11110000 )
1$
#60000
0$
b0 #
b0 '
0&
#65000
b10101010 !
b10101010 )
1$
#70000
0$
#75000
1$
#80000
0$
b11111111 #
b11111111 '
#85000
b1010101 !
b1010101 )
1$
#90000
0$
#95000
1$
#100000
0$
b1010 #
b1010 '
#105000
b11110000 !
b11110000 )
1$
