src/register.v
module register(
    input wire clk,
    input wire reset,
    input wire enable,
    input wire latch,
    input wire [7:0] data,
    output reg [7:0] reg_out
);

// instance
// register register_instance(
//     .clk(),
//     .reset(),
//     .data(),
//     .reg_out(),
//     .enable(),
//     .latch()
// );

reg[7:0] r;

always @(posedge clk ) begin
    if (reset) begin
        r <= 0;
    end else begin
        if (latch) begin
            r<=data;
        end
    end
end

always @(*) begin
    if(enable) begin
        reg_out = r;
    end else begin
        reg_out = 8'bz;
    end
end

endmodule

test/register_tb.v
module register_tb;
    // Inputs
    reg clk;
    reg reset;
    reg [7:0] data;
    reg enable;
    reg latch;

    // Outputs
    wire [7:0] reg_out;

    // Instantiate the Unit Under Test (UUT)
    register uut (
        .clk(clk), 
        .reset(reset), 
        .data(data), 
        .reg_out(reg_out), 
        .enable(enable), 
        .latch(latch)
    );

    initial begin
        // Initialize Inputs
        clk = 0;
        reset = 0;
        data = 0;
        enable = 0;
        latch = 0;

        // Generate VCD file
        $dumpfile("register_tb.vcd");
        $dumpvars(0, register_tb);

        // Reset the register
        reset = 1;
        #10;
        reset = 0;

        // Load value into register
        data = 8'hAA;  // Example data
        latch = 1;
        #10;
        latch = 0;

        // Enable output
        enable = 1;
        #10;

        // Change the data and latch again
        data = 8'h55;
        latch = 1;
        #10;
        latch = 0;

        // Disable output
        enable = 0;
        #10;

        // Finish simulation
        $finish;
    end

    always #5 clk = ~clk; // Generate clock signal

endmodule

vcd/register_tb.vcd
$date
	Sat Jun 15 23:08:51 2024
$end
$version
	Icarus Verilog
$end
$timescale
	1s
$end
$scope module register_tb $end
$var wire 8 ! reg_out [7:0] $end
$var reg 1 " clk $end
$var reg 8 # data [7:0] $end
$var reg 1 $ enable $end
$var reg 1 % latch $end
$var reg 1 & reset $end
$scope module uut $end
$var wire 1 " clk $end
$var wire 8 ' data [7:0] $end
$var wire 1 $ enable $end
$var wire 1 % latch $end
$var wire 1 & reset $end
$var reg 8 ( r [7:0] $end
$var reg 8 ) reg_out [7:0] $end
$upscope $end
$upscope $end
$enddefinitions $end
$comment Show the parameter values. $end
$dumpall
$end
#0
$dumpvars
bx )
bx (
b0 '
1&
0%
0$
b0 #
0"
bx !
$end
#5
b0 (
bz !
bz )
1"
#10
0"
1%
b10101010 #
b10101010 '
0&
#15
b10101010 (
1"
#20
0"
1$
0%
#25
b10101010 !
b10101010 )
1"
#30
0"
1%
b1010101 #
b1010101 '
#35
b1010101 !
b1010101 )
b1010101 (
1"
#40
0"
0$
0%
#45
bz !
bz )
1"
