src/register.v
module register (
    input wire clk,
    input wire reset,
    input wire latch,
    input wire inc,
    input wire [7:0] data,
    output reg [7:0] reg_out
);
    always @(posedge clk) begin
        if (reset) begin
            reg_out <= 8'h00; // Reset to 0
        end else if (latch) begin
            reg_out <= data; // Load with data
        end else if (inc) begin
            reg_out <= reg_out + 1'b1; // Increment
        end
    end

endmodule

test/register_tb.v
`timescale 1ns / 1ps

module register_tb;

    // Parameters
    parameter CLK_PERIOD = 10; // Clock period in time units

    // Signals
    reg clk;
    reg reset;
    reg latch;
    reg inc;
    reg [7:0] data;
    wire [7:0] reg_out;

    // Instantiate register module
    register dut (
        .clk(clk),
        .reset(reset),
        .latch(latch),
        .inc(inc),
        .data(data),
        .reg_out(reg_out)
    );

    // Stimulus
    initial begin
        clk = 0;
        $dumpfile("register_tb.vcd");
        $dumpvars(0, register_tb);

        // Reset test
        reset = 1;
        #20;
        reset = 0;
        #20;

        // Load data test
        data = 8'hAA;
        latch = 1;
        #20;
        latch = 0;
        #20;

        // Increment test
        inc = 1;
        #20;
        inc = 0;
        #20;

        // Further tests can be added here

        // End simulation
        #100;
        $finish;
    end

    always #5 clk = ~clk;

endmodule

vcd/register_tb.vcd
$date
	Sun Jun 16 23:40:15 2024
$end
$version
	Icarus Verilog
$end
$timescale
	1ps
$end
$scope module register_tb $end
$var wire 8 ! reg_out [7:0] $end
$var parameter 32 " CLK_PERIOD $end
$var reg 1 # clk $end
$var reg 8 $ data [7:0] $end
$var reg 1 % inc $end
$var reg 1 & latch $end
$var reg 1 ' reset $end
$scope module dut $end
$var wire 1 # clk $end
$var wire 8 ( data [7:0] $end
$var wire 1 % inc $end
$var wire 1 & latch $end
$var wire 1 ' reset $end
$var reg 8 ) reg_out [7:0] $end
$upscope $end
$upscope $end
$enddefinitions $end
$comment Show the parameter values. $end
$dumpall
b1010 "
$end
#0
$dumpvars
bx )
bx (
1'
x&
x%
bx $
0#
bx !
$end
#5000
b0 !
b0 )
1#
#10000
0#
#15000
1#
#20000
0#
0'
#25000
1#
#30000
0#
#35000
1#
#40000
0#
1&
b10101010 $
b10101010 (
#45000
b10101010 !
b10101010 )
1#
#50000
0#
#55000
1#
#60000
0#
0&
#65000
1#
#70000
0#
#75000
1#
#80000
0#
1%
#85000
b10101011 !
b10101011 )
1#
#90000
0#
#95000
b10101100 !
b10101100 )
1#
#100000
0#
0%
